Metadata-Version: 2.1
Name: scdna-replication-tools
Version: 0.0.1
Summary: Code for analyzing single-cell replication dynamics
Home-page: https://github.com/shahcompbio/scdna_replication_tools
Author: Adam Weiner (Shah Lab)
License-File: LICENSE
Requires-Dist: absl-py (==1.1.0)
Requires-Dist: adal (==1.2.2)
Requires-Dist: adjustText (==0.7.3)
Requires-Dist: alabaster (==0.7.12)
Requires-Dist: anndata (==0.7.8)
Requires-Dist: appnope (==0.1.2)
Requires-Dist: argon2-cffi (==20.1.0)
Requires-Dist: asn1crypto (==0.24.0)
Requires-Dist: astroid (==2.2.5)
Requires-Dist: async-generator (==1.10)
Requires-Dist: attrs (==20.3.0)
Requires-Dist: azure-batch (==10.0.0)
Requires-Dist: azure-common (==1.1.23)
Requires-Dist: azure-core (==1.11.0)
Requires-Dist: azure-identity (==1.5.0)
Requires-Dist: azure-keyvault (==1.1.0)
Requires-Dist: azure-nspkg (==3.0.2)
Requires-Dist: azure-storage (==0.36.0)
Requires-Dist: azure-storage-blob (==12.7.1)
Requires-Dist: azure-storage-common (==2.1.0)
Requires-Dist: Babel (==2.9.1)
Requires-Dist: backcall (==0.1.0)
Requires-Dist: backports-abc (==0.5)
Requires-Dist: backports.functools-lru-cache (==1.5)
Requires-Dist: backports.shutil-get-terminal-size (==1.0.0)
Requires-Dist: bamread (==0.0.11)
Requires-Dist: bcrypt (==3.1.7)
Requires-Dist: bleach (==3.3.0)
Requires-Dist: bokeh (==2.3.1)
Requires-Dist: brewer2mpl (==1.4.1)
Requires-Dist: cached-property (==1.5.2)
Requires-Dist: certifi (==2019.9.11)
Requires-Dist: cffi (==1.13.2)
Requires-Dist: chardet (==3.0.4)
Requires-Dist: Click (==7.0)
Requires-Dist: colorama (==0.4.4)
Requires-Dist: configparser (==3.5.0)
Requires-Dist: coreapi (==2.3.3)
Requires-Dist: coreschema (==0.0.4)
Requires-Dist: cryptography (==2.8)
Requires-Dist: cycler (==0.10.0)
Requires-Dist: Cython (==0.29.22)
Requires-Dist: daft (==0.1.2)
Requires-Dist: decorator (==4.4.1)
Requires-Dist: defusedxml (==0.6.0)
Requires-Dist: dill (==0.3.1.1)
Requires-Dist: Django (==1.11.16)
Requires-Dist: docker (==4.1.0)
Requires-Dist: docker-pycreds (==0.4.0)
Requires-Dist: docutils (==0.17.1)
Requires-Dist: entrypoints (==0.3)
Requires-Dist: enum34 (==1.1.6)
Requires-Dist: fire (==0.4.0)
Requires-Dist: flatbuffers (==2.0)
Requires-Dist: funcsigs (==1.0.2)
Requires-Dist: funsor (==0.4.3)
Requires-Dist: graphviz (==0.20)
Requires-Dist: h5py (==3.6.0)
Requires-Dist: hdbscan (==0.8.33)
Requires-Dist: hmmlearn (==0.2.5)
Requires-Dist: idna (==2.8)
Requires-Dist: imagesize (==1.2.0)
Requires-Dist: importlib-metadata (==4.4)
Requires-Dist: iniconfig (==1.1.1)
Requires-Dist: ipaddress (==1.0.22)
Requires-Dist: ipykernel (==5.5.0)
Requires-Dist: ipython (==7.9.0)
Requires-Dist: ipython-genutils (==0.2.0)
Requires-Dist: ipywidgets (==7.6.3)
Requires-Dist: isodate (==0.6.0)
Requires-Dist: isort (==4.3.17)
Requires-Dist: itypes (==1.1.0)
Requires-Dist: jedi (==0.15.1)
Requires-Dist: Jinja2 (==2.10.3)
Requires-Dist: jira (==2.0.0)
Requires-Dist: joblib (==1.0.1)
Requires-Dist: jsonschema (==3.2.0)
Requires-Dist: jupyter (==1.0.0)
Requires-Dist: jupyter-client (==6.1.12)
Requires-Dist: jupyter-console (==6.3.0)
Requires-Dist: jupyter-core (==4.7.1)
Requires-Dist: jupyterlab-pygments (==0.1.2)
Requires-Dist: jupyterlab-widgets (==1.0.0)
Requires-Dist: kiwisolver (==1.3.1)
Requires-Dist: lazy-object-proxy (==1.3.1)
Requires-Dist: lda (==2.0.0)
Requires-Dist: line-profiler (==3.5.1)
Requires-Dist: llvmlite (==0.36.0)
Requires-Dist: makefun (==1.14.0)
Requires-Dist: MarkupSafe (==1.1.1)
Requires-Dist: matplotlib (==3.3.4)
Requires-Dist: mccabe (==0.6.1)
Requires-Dist: mistune (==0.8.4)
Requires-Dist: mock (==3.0.5)
Requires-Dist: msal (==1.10.0)
Requires-Dist: msal-extensions (==0.3.0)
Requires-Dist: msrest (==0.6.21)
Requires-Dist: msrestazure (==0.6.2)
Requires-Dist: multipledispatch (==0.6.0)
Requires-Dist: mypy (==0.790)
Requires-Dist: mypy-extensions (==0.4.3)
Requires-Dist: mysqlclient (==2.1.0)
Requires-Dist: natsort (==8.0.0)
Requires-Dist: nbclient (==0.5.3)
Requires-Dist: nbconvert (==6.0.7)
Requires-Dist: nbformat (==5.1.2)
Requires-Dist: ncls (==0.0.63)
Requires-Dist: nest-asyncio (==1.5.1)
Requires-Dist: networkx (==2.4)
Requires-Dist: notebook (==6.2.0)
Requires-Dist: numba (==0.53.0)
Requires-Dist: numexpr (==2.7.3)
Requires-Dist: numpy (==1.21.4)
Requires-Dist: oauthlib (==3.1.0)
Requires-Dist: openapi-codec (==1.3.2)
Requires-Dist: opt-einsum (==3.3.0)
Requires-Dist: packaging (==20.3)
Requires-Dist: pandas (==1.3.4)
Requires-Dist: pandocfilters (==1.4.3)
Requires-Dist: paramiko (==2.6.0)
Requires-Dist: parso (==0.5.1)
Requires-Dist: pathlib2 (==2.3.2)
Requires-Dist: patsy (==0.5.1)
Requires-Dist: pbr (==3.1.1)
Requires-Dist: pexpect (==4.7.0)
Requires-Dist: pickleshare (==0.7.5)
Requires-Dist: pika (==1.1.0)
Requires-Dist: Pillow (==8.1.2)
Requires-Dist: pluggy (==1.0.0)
Requires-Dist: portalocker (==1.5.2)
Requires-Dist: prometheus-client (==0.9.0)
Requires-Dist: prompt-toolkit (==2.0.10)
Requires-Dist: ptyprocess (==0.6.0)
Requires-Dist: py (==1.10.0)
Requires-Dist: pyasn1 (==0.4.5)
Requires-Dist: pyBigWig (==0.3.22)
Requires-Dist: pycparser (==2.19)
Requires-Dist: pyfaidx (==0.6.4)
Requires-Dist: Pygments (==2.4.2)
Requires-Dist: PyJWT (==1.7.1)
Requires-Dist: pyliftover (==0.4)
Requires-Dist: pylint (==2.3.1)
Requires-Dist: PyNaCl (==1.3.0)
Requires-Dist: pynndescent (==0.5.2)
Requires-Dist: pyparsing (==2.4.6)
Requires-Dist: pypeliner (==0.5.24)
Requires-Dist: pyranges (==0.0.113)
Requires-Dist: pyranges-db (==0.0.7)
Requires-Dist: pyrle (==0.0.33)
Requires-Dist: pyro-api (==0.1.2)
Requires-Dist: pyro-ppl (==1.8.2)
Requires-Dist: pyrsistent (==0.17.3)
Requires-Dist: pysam (==0.18.0)
Requires-Dist: pytest (==6.2.5)
Requires-Dist: python-dateutil (==2.8.1)
Requires-Dist: pytz (==2019.3)
Requires-Dist: PyYAML (==5.1.2)
Requires-Dist: pyzmq (==22.0.3)
Requires-Dist: qtconsole (==5.0.3)
Requires-Dist: QtPy (==1.9.0)
Requires-Dist: requests (==2.22.0)
Requires-Dist: requests-oauthlib (==1.3.0)
Requires-Dist: requests-toolbelt (==0.9.1)
Requires-Dist: rlipython (==0.1.2)
Requires-Dist: ruptures (==1.1.6)
Requires-Dist: saltant-py (==0.4.0)
Requires-Dist: scandir (==1.9.0)
Requires-Dist: scikit-learn (==0.24.1)
Requires-Dist: scipy (==1.6.1)
Requires-Dist: seaborn (==0.11.1)
Requires-Dist: Send2Trash (==1.5.0)
Requires-Dist: simplegeneric (==0.8.1)
Requires-Dist: singledispatch (==3.4.0.3)
Requires-Dist: six (==1.13.0)
Requires-Dist: snowballstemmer (==2.1.0)
Requires-Dist: sorted-nearest (==0.0.39)
Requires-Dist: Sphinx (==5.1.1)
Requires-Dist: sphinxcontrib-serializinghtml (==1.1.5)
Requires-Dist: sphinxcontrib-websupport (==1.2.4)
Requires-Dist: statannot (==0.2.3)
Requires-Dist: statsmodels (==0.12.2)
Requires-Dist: subprocess32 (==3.5.3)
Requires-Dist: tables (==3.6.1)
Requires-Dist: tabulate (==0.8.9)
Requires-Dist: termcolor (==1.1.0)
Requires-Dist: terminado (==0.9.3)
Requires-Dist: testpath (==0.4.4)
Requires-Dist: threadpoolctl (==2.1.0)
Requires-Dist: toml (==0.10.2)
Requires-Dist: torch (==1.12.1)
Requires-Dist: torchvision (==0.13.1)
Requires-Dist: tornado (==6.1)
Requires-Dist: tqdm (==4.64.0)
Requires-Dist: traitlets (==4.3.3)
Requires-Dist: typed-ast (==1.4.3)
Requires-Dist: typing-extensions (==3.7.4.3)
Requires-Dist: umap-learn (==0.5.2)
Requires-Dist: uritemplate (==3.0.0)
Requires-Dist: urllib3 (==1.25.7)
Requires-Dist: wcwidth (==0.1.7)
Requires-Dist: webencodings (==0.5.1)
Requires-Dist: websocket-client (==0.56.0)
Requires-Dist: widgetsnbextension (==3.5.1)
Requires-Dist: wrapt (==1.11.1)
Requires-Dist: xlrd (==1.2.0)
Requires-Dist: zipp (==3.4.1)
